napari_pixseq/__init__.py
napari_pixseq/_version.py
napari_pixseq/napari.yaml
napari_pixseq/pixseq_widget.py
napari_pixseq/GUI/__init__.py
napari_pixseq/GUI/pixseq_ui.py
napari_pixseq/GUI/pixseq_ui.ui
napari_pixseq/_tests/__init__.py
napari_pixseq/_tests/test_widget.py
napari_pixseq/dev/__init__.py
napari_pixseq/dev/ebfret_IO_dev.py
napari_pixseq/dev/refactor.py
napari_pixseq/dev/spot_mask_dev.py
napari_pixseq/funcs/__init__.py
napari_pixseq/funcs/pixseq_align_utils.py
napari_pixseq/funcs/pixseq_cluster_utils.py
napari_pixseq/funcs/pixseq_colocalize_utils.py
napari_pixseq/funcs/pixseq_events.py
napari_pixseq/funcs/pixseq_export_images_utils.py
napari_pixseq/funcs/pixseq_export_traces_utils.py
napari_pixseq/funcs/pixseq_filter_utils.py
napari_pixseq/funcs/pixseq_import_utils.py
napari_pixseq/funcs/pixseq_loc_utils.py
napari_pixseq/funcs/pixseq_picasso_detect.py
napari_pixseq/funcs/pixseq_plot_utils.py
napari_pixseq/funcs/pixseq_segmentation_events.py
napari_pixseq/funcs/pixseq_segmentation_utils.py
napari_pixseq/funcs/pixseq_simple_analysis_utils.py
napari_pixseq/funcs/pixseq_temporal_filtering.py
napari_pixseq/funcs/pixseq_trace_compute_utils.py
napari_pixseq/funcs/pixseq_tracking_utils.py
napari_pixseq/funcs/pixseq_transform_utils.py
napari_pixseq/funcs/pixseq_undrift_utils.py
napari_pixseq/funcs/pixseq_utils_compute.py
napari_pixseq/scripts/pypi
napari_PixSeq-1.0.3.dist-info/LICENSE
napari_PixSeq-1.0.3.dist-info/METADATA
napari_PixSeq-1.0.3.dist-info/WHEEL
napari_PixSeq-1.0.3.dist-info/entry_points.txt
napari_PixSeq-1.0.3.dist-info/top_level.txt
napari_PixSeq-1.0.3.dist-info/RECORD
