Metadata-Version: 2.1
Name: napari-PixSeq
Version: 1.0.3
Summary: A Napari plugin for extracting time series traces from Single Molecule Localisation Microsocpy (SMLM) data.
Home-page: https://github.com/piedrro/napari-PixSeq
Author: Piers Turner
Author-email: piers.turner@physics.ox.ac.uk
License: MIT
Project-URL: Bug Tracker, https://github.com/piedrro/napari-PixSeq/issues
Project-URL: Documentation, https://github.com/piedrro/napari-PixSeq#README.md
Project-URL: Source Code, https://github.com/piedrro/napari-PixSeq
Project-URL: User Support, https://github.com/piedrro/napari-PixSeq/issues
Classifier: Development Status :: 2 - Pre-Alpha
Classifier: Framework :: napari
Classifier: Intended Audience :: Developers
Classifier: License :: OSI Approved :: MIT License
Classifier: Operating System :: OS Independent
Classifier: Programming Language :: Python
Classifier: Programming Language :: Python :: 3
Classifier: Programming Language :: Python :: 3 :: Only
Classifier: Programming Language :: Python :: 3.8
Classifier: Programming Language :: Python :: 3.9
Classifier: Programming Language :: Python :: 3.10
Classifier: Topic :: Scientific/Engineering :: Image Processing
Requires-Python: >=3.8
License-File: LICENSE
Requires-Dist: napari[all]
Requires-Dist: numpy
Requires-Dist: magicgui
Requires-Dist: qtpy
Requires-Dist: scipy
Requires-Dist: pyqtgraph
Requires-Dist: picassosr
Requires-Dist: pandas
Requires-Dist: matplotlib
Requires-Dist: opencv-python
Requires-Dist: tqdm
Requires-Dist: originpro
Requires-Dist: pyqt5-tools
Requires-Dist: torch
Requires-Dist: cellpose >=3.0.1
Requires-Dist: omnipose
Requires-Dist: trackpy
Requires-Dist: shapely
Requires-Dist: astropy
Provides-Extra: testing
Requires-Dist: tox ; extra == 'testing'
Requires-Dist: pytest ; extra == 'testing'
Requires-Dist: pytest-cov ; extra == 'testing'
Requires-Dist: pytest-qt ; extra == 'testing'
Requires-Dist: napari ; extra == 'testing'
Requires-Dist: pyqt5 ; extra == 'testing'
